stoobly_agent/__init__.py
stoobly_agent/__main__.py
stoobly_agent/app/__init__.py
stoobly_agent/app/api/__init__.py
stoobly_agent/app/api/application_http_request_handler.py
stoobly_agent/app/api/bodies_controller.py
stoobly_agent/app/api/configs_controller.py
stoobly_agent/app/api/headers_controller.py
stoobly_agent/app/api/proxy_controller.py
stoobly_agent/app/api/query_params_controller.py
stoobly_agent/app/api/replayed_response_headers_controller.py
stoobly_agent/app/api/replayed_responses_controller.py
stoobly_agent/app/api/requests_controller.py
stoobly_agent/app/api/response_headers_controller.py
stoobly_agent/app/api/responses_controller.py
stoobly_agent/app/api/routes.py
stoobly_agent/app/api/scenarios_controller.py
stoobly_agent/app/api/simple_http_request_handler.py
stoobly_agent/app/api/statuses_controller.py
stoobly_agent/app/cli/__init__.py
stoobly_agent/app/cli/ca_cert_cli.py
stoobly_agent/app/cli/config_cli.py
stoobly_agent/app/cli/decorators/__init__.py
stoobly_agent/app/cli/decorators/config.py
stoobly_agent/app/cli/decorators/exec.py
stoobly_agent/app/cli/dev_tools_cli.py
stoobly_agent/app/cli/endpoint_cli.py
stoobly_agent/app/cli/feature_cli.py
stoobly_agent/app/cli/handlers/request_cli_handler.py
stoobly_agent/app/cli/handlers/scenario_cli_handler.py
stoobly_agent/app/cli/helpers/__init__.py
stoobly_agent/app/cli/helpers/certificate_authority.py
stoobly_agent/app/cli/helpers/context.py
stoobly_agent/app/cli/helpers/endpoint_facade.py
stoobly_agent/app/cli/helpers/endpoints_apply_context.py
stoobly_agent/app/cli/helpers/endpoints_apply_service.py
stoobly_agent/app/cli/helpers/endpoints_import_context.py
stoobly_agent/app/cli/helpers/endpoints_import_service.py
stoobly_agent/app/cli/helpers/feature_flags.py
stoobly_agent/app/cli/helpers/handle_config_update_service.py
stoobly_agent/app/cli/helpers/handle_mock_service.py
stoobly_agent/app/cli/helpers/handle_replay_service.py
stoobly_agent/app/cli/helpers/handle_test_service.py
stoobly_agent-1.13.6.dist-info/METADATA
stoobly_agent-1.13.6.dist-info/WHEEL
stoobly_agent-1.13.6.dist-info/entry_points.txt
stoobly_agent-1.13.6.dist-info/licenses/LICENSE
stoobly_agent-1.13.6.dist-info/RECORD
