Metadata-Version: 2.4
Name: stoobly-agent
Version: 1.13.6
Summary: Record, mock, and test HTTP(s) requests. CLI agent for Stoobly
License: Apache-2.0
License-File: LICENSE
Author: Matt Le
Author-email: themathewle@gmail.com
Requires-Python: >=3.10,<4.0
Classifier: License :: OSI Approved :: Apache Software License
Classifier: Programming Language :: Python :: 3
Classifier: Programming Language :: Python :: 3.10
Classifier: Programming Language :: Python :: 3.11
Classifier: Programming Language :: Python :: 3.12
Classifier: Programming Language :: Python :: 3.13
Classifier: Programming Language :: Python :: 3.14
Requires-Dist: click (>=8.1.0,<9.0.0)
Requires-Dist: diff-match-patch (>=20241021,<20241022)
Requires-Dist: distro (>=1.9.0,<1.10)
Requires-Dist: dnspython (>=2.7.0,<2.8)
Requires-Dist: docker (>=7.1.0,<8.0)
Requires-Dist: filelock (>=3.19.1,<4.0.0)
Requires-Dist: httptools (>=0.4.0)
Requires-Dist: jmespath (>=1.0.0)
Requires-Dist: mergedeep (>=1.3,<1.4)
Requires-Dist: mitmproxy (>=11.0.2,<11.1.0)
Requires-Dist: multipart (>=1.2.1,<1.3)
Requires-Dist: openapi-core (>=0.19.0,<0.20.0)
Requires-Dist: python-dotenv (>=1.0.1,<2.0.0)
Requires-Dist: pyyaml (>=6.0.1)
Requires-Dist: requests (>=2.31.0)
Requires-Dist: stoobly_orator (>=0.9.12)
Requires-Dist: tabulate (>=0.8.8)
Requires-Dist: watchdog (>=6.0.0,<=6.1.0)
Requires-Dist: yamale (>=6.0.0,<=7.0.0)
Project-URL: Homepage, https://github.com/Stoobly/stoobly-agent
